rpi2mqtt/__init__.py
rpi2mqtt/base.py
rpi2mqtt/binary.py
rpi2mqtt/config.py
rpi2mqtt/event_loop.py
rpi2mqtt/ibeacon.py
rpi2mqtt/math.py
rpi2mqtt/mqtt.py
rpi2mqtt/mqtt_test.py
rpi2mqtt/paho_eg.py
rpi2mqtt/switch.py
rpi2mqtt/temperature.py
rpi2mqtt/tests.py
rpi2mqtt/thermostat.py
rpi2mqtt/version.py
rpi2mqtt-0.3.3.dist-info/METADATA
rpi2mqtt-0.3.3.dist-info/WHEEL
rpi2mqtt-0.3.3.dist-info/entry_points.txt
rpi2mqtt-0.3.3.dist-info/top_level.txt
rpi2mqtt-0.3.3.dist-info/RECORD
