Metadata-Version: 2.1
Name: rpi2mqtt
Version: 0.3.3
Summary: UNKNOWN
Home-page: https://github.com/kirbs-/rpi2mqtt
Author: Chris Kirby
Author-email: kirbycm@gmail.com
License: MIT
Keywords: raspberrypi mqtt GPIO home_automation home_assistant
Platform: UNKNOWN
Classifier: Development Status :: 4 - Beta
Classifier: Intended Audience :: Developers
Classifier: Topic :: Scientific/Engineering
Classifier: License :: OSI Approved :: MIT License
Classifier: Programming Language :: Python :: 3.6
Classifier: Programming Language :: Python :: 3.7
Classifier: Programming Language :: Python :: 3.8
Classifier: Programming Language :: Python :: 3.9
Requires-Dist: dotmap
Requires-Dist: pyyaml
Requires-Dist: paho-mqtt
Requires-Dist: Adafruit-DHT
Requires-Dist: RPi.bme280
Requires-Dist: pathlib
Requires-Dist: smbus2
Requires-Dist: beacontools
Requires-Dist: RPi.GPIO
Requires-Dist: pendulum (==2.1.1)
Requires-Dist: poetry
